pydesk/__init__.py
pydesk/backup.py
pydesk/expenses.py
pydesk/main.py
pydesk/notes.py
pydesk/tasks.py
pydesk/utils/__init__.py
pydesk/utils/a.py
pydesk/utils/file_manager.py
pydesk/utils/logger.py
pydesk/utils/logger1.py
pydeskpro-1.0.1.dist-info/licenses/LICENSE
pydeskpro-1.0.1.dist-info/METADATA
pydeskpro-1.0.1.dist-info/WHEEL
pydeskpro-1.0.1.dist-info/entry_points.txt
pydeskpro-1.0.1.dist-info/top_level.txt
pydeskpro-1.0.1.dist-info/RECORD
