Metadata-Version: 2.4
Name: pydeskpro
Version: 1.0.1
Home-page: https://github.com/shafiqul8/pydeskpro
Author: SHAFIQUL ISLAM
Author-email: shafiqul.cmt@gmail.com
License: MIT
License-File: LICENSE
Requires-Dist: click
Requires-Dist: rich
Dynamic: author
Dynamic: author-email
Dynamic: home-page
Dynamic: license-file
